netbox_acls/CODEOWNERS
netbox_acls/__init__.py
netbox_acls/choices.py
netbox_acls/constants.py
netbox_acls/filtersets.py
netbox_acls/navigation.py
netbox_acls/tables.py
netbox_acls/urls.py
netbox_acls/views.py
netbox_acls/api/__init__.py
netbox_acls/api/serializers.py
netbox_acls/api/urls.py
netbox_acls/api/views.py
netbox_acls/forms/__init__.py
netbox_acls/forms/bulk_edit.py
netbox_acls/forms/filtersets.py
netbox_acls/forms/models.py
netbox_acls/graphql/__init__.py
netbox_acls/graphql/enums.py
netbox_acls/graphql/schema.py
netbox_acls/graphql/types.py
netbox_acls/graphql/filters/__init__.py
netbox_acls/graphql/filters/access_list_rules.py
netbox_acls/graphql/filters/access_lists.py
netbox_acls/migrations/0001_initial.py
netbox_acls/migrations/0002_alter_accesslist_options_and_more.py
netbox_acls/migrations/0003_netbox_acls.py
netbox_acls/migrations/0004_netbox_acls.py
netbox_acls/migrations/__init__.py
netbox_acls/models/__init__.py
netbox_acls/models/access_list_rules.py
netbox_acls/models/access_lists.py
netbox_acls/templates/inc/view_tab.html
netbox_acls/templates/netbox_acls/accesslist.html
netbox_acls/templates/netbox_acls/aclextendedrule.html
netbox_acls/templates/netbox_acls/aclinterfaceassignment.html
netbox_acls/templates/netbox_acls/aclstandardrule.html
netbox_acls/tests/__init__.py
netbox_acls/tests/api/__init__.py
netbox_acls/tests/api/test_access_list_rules.py
netbox_acls/tests/api/test_access_lists.py
netbox_acls/tests/api/test_app.py
netbox_acls/tests/models/__init__.py
netbox_acls/tests/models/base.py
netbox_acls/tests/models/test_accesslists.py
netbox_acls/tests/models/test_aclinterfaceassignments.py
netbox_acls/tests/models/test_extendedrules.py
netbox_acls/tests/models/test_standardrules.py
netbox_acls-1.9.1.dist-info/licenses/LICENSE.txt
netbox_acls-1.9.1.dist-info/METADATA
netbox_acls-1.9.1.dist-info/WHEEL
netbox_acls-1.9.1.dist-info/top_level.txt
netbox_acls-1.9.1.dist-info/RECORD
