Metadata-Version: 2.4
Name: netbox-acls
Version: 1.9.1
License: 
Project-URL: Documentation, https://github.com/netbox-community/netbox-acls/blob/dev/README.md
Project-URL: Source, https://github.com/netbox-community/netbox-acls/
Project-URL: Tracker, https://github.com/netbox-community/netbox-acls/issues
Keywords: netbox,netbox-plugin
Classifier: Development Status :: 5 - Production/Stable
Classifier: Intended Audience :: Developers
Classifier: Natural Language :: English
Classifier: Programming Language :: Python :: 3 :: Only
Classifier: Programming Language :: Python :: 3.10
Classifier: Programming Language :: Python :: 3.11
Classifier: Programming Language :: Python :: 3.12
Classifier: Intended Audience :: System Administrators
Classifier: Intended Audience :: Telecommunications Industry
Classifier: Framework :: Django
Classifier: Topic :: System :: Networking
Classifier: Topic :: Internet
Requires-Python: >=3.10.0
License-File: LICENSE.txt
Dynamic: license-file
